siape_tool/__init__.py
siape_tool/cli.py
siape_tool/main.py
siape_tool/scraper.py
siape_tool/utils/__init__.py
siape_tool/utils/api_calls_dicts.py
siape_tool/utils/combs_dict.py
siape_tool/utils/constants.py
siape_tool/utils/errors.py
siape_tool/utils/paths.py
siape_cli-0.2.2.dist-info/LICENSE
siape_cli-0.2.2.dist-info/METADATA
siape_cli-0.2.2.dist-info/WHEEL
siape_cli-0.2.2.dist-info/entry_points.txt
siape_cli-0.2.2.dist-info/RECORD
